ebx_progressbar/__init__.py
ebx_progressbar-1.1.1.dist-info/LICENSE
ebx_progressbar-1.1.1.dist-info/METADATA
ebx_progressbar-1.1.1.dist-info/WHEEL
ebx_progressbar-1.1.1.dist-info/top_level.txt
ebx_progressbar-1.1.1.dist-info/RECORD
