Metadata-Version: 2.1
Name: ebx-progressbar
Version: 1.1.1
Summary: Print 2 types of progressbar
Home-page: https://github.com/faustobranco/ebx_progressbar
Author: Fausto Branco
Author-email: fausto.branco@gmail.com
License: UNKNOWN
Project-URL: Bug Tracker, https://github.com/faustobranco/ebx_progressbar/issues
Platform: UNKNOWN
Classifier: Programming Language :: Python :: 3
Classifier: License :: OSI Approved :: MIT License
Classifier: Operating System :: OS Independent
Requires-Python: >=3.6
